matinfwebapi/Api.py
matinfwebapi/__init__.py
crc1625_api-0.1.11.dist-info/METADATA
crc1625_api-0.1.11.dist-info/WHEEL
crc1625_api-0.1.11.dist-info/top_level.txt
crc1625_api-0.1.11.dist-info/RECORD
