Metadata-Version: 2.4
Name: crc1625-api
Version: 0.1.11
Summary: Python wrapper for the CRC 1625 MatInf VRO API
Home-page: https://gitlab.ruhr-uni-bochum.de/icams-mids/crc1625rdmswrapper
Author: Doaa Mohamed
Author-email: Doaa Mohamed <doaamahmoud262@yahoo.com>
License: MIT
Project-URL: Homepage, https://pypi.org/project/crc1625-api/
Project-URL: Source, https://gitlab.ruhr-uni-bochum.de/icams-mids/crc1625rdmswrapper
Project-URL: Tracker, https://gitlab.ruhr-uni-bochum.de/icams-mids/crc1625rdmswrapper/issues
Keywords: materials,FAIR,API,CRC165,data-management
Classifier: Programming Language :: Python :: 3
Classifier: Programming Language :: Python :: 3 :: Only
Classifier: License :: OSI Approved :: MIT License
Classifier: Operating System :: OS Independent
Requires-Python: >=3.7
Requires-Dist: requests>=2.28
Requires-Dist: pandas>=1.5
Requires-Dist: openpyxl>=3.1
Requires-Dist: numpy>=1.22
Requires-Dist: scipy>=1.8
Dynamic: author
Dynamic: home-page
Dynamic: requires-python
